protomake/__init__.py
protomake/__main__.py
protomake/protomake.py
protomake-1.0.0.dist-info/WHEEL
protomake-1.0.0.dist-info/METADATA
protomake-1.0.0.dist-info/RECORD
