Metadata-Version: 2.1
Name: protomake
Version: 1.0.0
Summary: Generate .py from .proto.
Author: Manuel Šarić
Author-email: manujelko@gmail.com
Requires-Python: >=3.8,<4.0
Classifier: Programming Language :: Python :: 3
Classifier: Programming Language :: Python :: 3.10
Classifier: Programming Language :: Python :: 3.8
Classifier: Programming Language :: Python :: 3.9
Requires-Dist: click (>=8.0.3,<9.0.0)
Requires-Dist: grpcio-tools (>=1.43.0,<2.0.0)
Requires-Dist: mypy-protobuf (>=3.2.0,<4.0.0)
